adafruit_debug_i2c.py
adafruit_circuitpython_debug_i2c-1.2.22.dist-info/licenses/LICENSE
adafruit_circuitpython_debug_i2c-1.2.22.dist-info/METADATA
adafruit_circuitpython_debug_i2c-1.2.22.dist-info/WHEEL
adafruit_circuitpython_debug_i2c-1.2.22.dist-info/top_level.txt
adafruit_circuitpython_debug_i2c-1.2.22.dist-info/RECORD
