Metadata-Version: 2.4
Name: adafruit-circuitpython-debug-i2c
Version: 1.2.22
Summary: Wrapper library for debugging I2C.
Author-email: Adafruit Industries <circuitpython@adafruit.com>
License: MIT
Project-URL: Homepage, https://github.com/adafruit/Adafruit_CircuitPython_Debug_I2C
Keywords: adafruit,blinka,circuitpython,micropython,debug_i2c,i2c,debug
Classifier: Intended Audience :: Developers
Classifier: Topic :: Software Development :: Libraries
Classifier: Topic :: Software Development :: Embedded Systems
Classifier: Topic :: System :: Hardware
Classifier: License :: OSI Approved :: MIT License
Classifier: Programming Language :: Python :: 3
License-File: LICENSE
Requires-Dist: Adafruit-Blinka>=7.0.0
Requires-Dist: adafruit-circuitpython-typing
Provides-Extra: optional
Dynamic: license-file
